skglm/__init__.py
skglm/covariance.py
skglm/cv.py
skglm/estimators.py
skglm/datafits/__init__.py
skglm/datafits/base.py
skglm/datafits/group.py
skglm/datafits/multi_task.py
skglm/datafits/single_task.py
skglm/experimental/__init__.py
skglm/experimental/_plot_sqrt_lasso.py
skglm/experimental/pdcd_ws.py
skglm/experimental/quantile_huber.py
skglm/experimental/quantile_regression.py
skglm/experimental/reweighted.py
skglm/experimental/sqrt_lasso.py
skglm/experimental/tests/test_quantile_huber.py
skglm/experimental/tests/test_quantile_regression.py
skglm/experimental/tests/test_reweighted.py
skglm/experimental/tests/test_sqrt_lasso.py
skglm/penalties/__init__.py
skglm/penalties/base.py
skglm/penalties/block_separable.py
skglm/penalties/non_separable.py
skglm/penalties/separable.py
skglm/solvers/__init__.py
skglm/solvers/anderson_cd.py
skglm/solvers/base.py
skglm/solvers/common.py
skglm/solvers/fista.py
skglm/solvers/gram_cd.py
skglm/solvers/group_bcd.py
skglm/solvers/group_prox_newton.py
skglm/solvers/lbfgs.py
skglm/solvers/multitask_bcd.py
skglm/solvers/prox_newton.py
skglm/tests/test_covariance.py
skglm/tests/test_cv.py
skglm/tests/test_datafits.py
skglm/tests/test_docstring_parameters.py
skglm/tests/test_estimators.py
skglm/tests/test_fista.py
skglm/tests/test_gram_solver.py
skglm/tests/test_group.py
skglm/tests/test_lbfgs_solver.py
skglm/tests/test_penalties.py
skglm/tests/test_prox_newton.py
skglm/tests/test_sparse_ops.py
skglm/tests/test_validation.py
skglm/utils/__init__.py
skglm/utils/anderson.py
skglm/utils/data.py
skglm/utils/jit_compilation.py
skglm/utils/prox_funcs.py
skglm/utils/sparse_ops.py
skglm/utils/validation.py
skglm-0.5.dist-info/METADATA
skglm-0.5.dist-info/WHEEL
skglm-0.5.dist-info/top_level.txt
skglm-0.5.dist-info/RECORD
