Metadata-Version: 2.4
Name: skglm
Version: 0.5
Summary: A fast and modular scikit-learn replacement for generalized linear models
Author-email: Mathurin Massias <mathurin.massias@gmail.com>, Badr Moufad <badr.moufad@emines.um6p.ma>, Pierre-Antoine Bannier <pierreantoine.bannier@gmail.com>, Quentin Bertrand <quentin.bertrand@mila.quebec>, Quentin Klopfenstein <quentin.klopfenstein@uni.lu>
License: BSD (3-Clause)
Project-URL: Homepage, https://contrib.scikit-learn.org/skglm
Project-URL: Source, https://github.com/scikit-learn-contrib/skglm.git
Classifier: Programming Language :: Python :: 3 :: Only
Classifier: Programming Language :: Python :: 3.9
Classifier: Programming Language :: Python :: 3.10
Classifier: Programming Language :: Python :: 3.11
Classifier: Programming Language :: Python :: 3.12
Classifier: Programming Language :: Python :: 3.13
Requires-Python: >=3.9
Requires-Dist: numpy>=1.12
Requires-Dist: numba
Requires-Dist: scikit-learn>=1.6
Requires-Dist: scipy>=0.18.0
Provides-Extra: test
Requires-Dist: pytest; extra == "test"
Requires-Dist: flake8; extra == "test"
Requires-Dist: coverage; extra == "test"
Requires-Dist: numpydoc; extra == "test"
Requires-Dist: celer; extra == "test"
Provides-Extra: doc
Requires-Dist: benchopt; extra == "doc"
Requires-Dist: libsvmdata>=0.2; extra == "doc"
Requires-Dist: matplotlib>=2.0.0; extra == "doc"
Requires-Dist: myst_parser; extra == "doc"
Requires-Dist: numpydoc; extra == "doc"
Requires-Dist: pillow; extra == "doc"
Requires-Dist: sphinx-bootstrap-theme; extra == "doc"
Requires-Dist: sphinx_copybutton; extra == "doc"
Requires-Dist: sphinx-gallery; extra == "doc"
Requires-Dist: sphinx-design; extra == "doc"
Requires-Dist: pytest; extra == "doc"
Requires-Dist: lifelines; extra == "doc"
Requires-Dist: pydata_sphinx_theme; extra == "doc"
Requires-Dist: sphinx-sitemap; extra == "doc"
Requires-Dist: sphinxext-opengraph; extra == "doc"
